{
  "course": {
    "name": "🧱 HTML - Linguagem de marcação para sites na internet",
    "image": {
      "desktop": "/vitrine-ml5/mlab5/images/banner_frontend_desktop.png",
      "tablet": "/vitrine-ml5/mlab5/images/banner_frontend_tablet.png",
      "mobile": "/vitrine-ml5/mlab5/images/banner_frontend_mobile.png"
    },
    "articles": [
      {
        "position": 1,
        "headline": "Comparação com exemplo cotidiano: etiqueta",
        "text": "Funciona como uma etiqueta, no início tem a indicação de onde vai a costura inicial deve ser feita, e abaixo onde vai a costura final. Entre essas marcações existem outras informações marcadas.",
        "alternativeHeadline": "Informações na etiqueta:",
        "list": [
          "Nome da empresa",
          "CNPJ",
          "Local de produção",
          "Material",
          "Manuseio",
          "Tamanho",
          "Marcas de corte"
        ]
      },
      {
        "position": 2,
        "image": {
          "desktop": "/vitrine-ml5/mlab5/cursos/html5/01/images/etiqueta_desktop.png",
          "tablet": "/vitrine-ml5/mlab5/cursos/html5/01/images/etiqueta_tablet.png",
          "mobile": "/vitrine-ml5/mlab5/cursos/html5/01/images/etiqueta_mobile.png",
          "caption": "Etiqueta como metáfora de marcação"
        }
      },
      {
        "position": 3,
        "headline": "Tag's, marcadores de exemplo",
        "text": "No exemplo de página a seguir, no início e no seu fim é indicado pela marcação <html> É possível notar que a página tem duas partes distintas bem aparente. A “cabeçalho” da página <head> O corpo da página <body> No corpo ficam marcações bem perceptíveis, diferente do “cabeçalho”."
      },
      {
        "position": 4,
        "alternativeHeadline": "Exemplo",
        "subheadline": "Papeis desempenhados por essas tag's:",
        "programmingLanguage": "HTML",
        "code": [
          "<!DOCTYPE html> – Tipo do documento;",
          "<html> – Raiz do documento;",
          "<head> – <title>, <meta>, <link>",
          "<body> – Conteúdo visível;",
          "<h1> – Título;",
          "<p> – Parágrafo;",
          "<h2> – Sub-título."
        ]
      },
      {
        "position": 5,
        "image": {
          "src": "/vitrine-ml5/mlab5/cursos/html5/01/images/exemplo.png",
          "caption": "Estrutura básica de uma página HTML"
        }
      }
    ],
    "exercise": {
      "headline": "Exercício 01 de HTML",
      "text": "Crie uma página usando HTML com:",
      "steps": [
        "Título: O Caminho do Desenvolvimento Front-End",
        "Parágrafo: O desenvolvimento front-end é a arte de transformar ideias em experiências visuais e interativas. Para quem está iniciando, a jornada começa com compreender HTML, CSS e JavaScript.",
        "Subtítulo: Fundamentos Essenciais",
        "HTML é a espinha dorsal de qualquer página web, definindo a estrutura e o conteúdo. CSS traz vida ao design, ajustando cores, fontes e layouts. JavaScript dá movimento e lógica à interface, criando interatividade."
      ]
    },
    "controls": {
      "templates": [
        "/vitrine-ml5/mlab5/templates/classico.html",
        "/vitrine-ml5/mlab5/templates/moderno.html",
        "/vitrine-ml5/mlab5/templates/dark_mode.html"
      ],
      "styles": {
        "background": null,
        "foreground": null,
        "fontFamily": null
      }
    },
    "playground": {
      "url": "/vitrine-ml5/mlab5/playground"
    }
  }
}
